vmi485tousb/__init__.py
vmi485tousb/_uartChannel.py
vmiconfig/__init__.py
vmiconfig/_config.py
vmiiputil/__init__.py
vmiiputil/_iputil.py
vmilog/__init__.py
vmilog/_logging.py
vmimpeg/__init__.py
vmimpeg/_stream.py
vmimqtt/__init__.py
vmimqtt/_mqttchannel.py
vmilog_py-1.0.2.dist-info/LICENSE
vmilog_py-1.0.2.dist-info/METADATA
vmilog_py-1.0.2.dist-info/WHEEL
vmilog_py-1.0.2.dist-info/top_level.txt
vmilog_py-1.0.2.dist-info/RECORD
