Metadata-Version: 2.1
Name: vmilog-py
Version: 1.0.2
Summary: log library for vmilabs
Home-page: https://github.com/openvmi/vmilog-py
Author: vmilabs
Author-email: zeekzhou@163.com
License: Apache-2.0
Keywords: vmilabs log sdk
Requires-Python: >=3.6
License-File: LICENSE
Requires-Dist: pyserial
Requires-Dist: paho-mqtt
